DeployBlueprint/AWS.py
DeployBlueprint/Atlas.py
DeployBlueprint/ChangeManagement.py
DeployBlueprint/Logger.py
DeployBlueprint/Table.py
DeployBlueprint/Tasks.py
DeployBlueprint/__init__.py
DeployBlueprint-0.8.13.dist-info/LICENSE
DeployBlueprint-0.8.13.dist-info/METADATA
DeployBlueprint-0.8.13.dist-info/WHEEL
DeployBlueprint-0.8.13.dist-info/entry_points.txt
DeployBlueprint-0.8.13.dist-info/top_level.txt
DeployBlueprint-0.8.13.dist-info/RECORD
