Metadata-Version: 2.1
Name: DeployBlueprint
Version: 0.8.13
Summary: A basic tool to deploy AWS Instances and MongoDB Atlas Clusters for when using Cloud Formation, Terraform, Habitat, or others is overkill.
Home-page: https://github.com/graboskyc/DeployBlueprint
Author: graboskyc
Author-email: chris@grabosky.net
License: UNKNOWN
Platform: UNKNOWN
Requires-Dist: paramiko
Requires-Dist: scp
Requires-Dist: ConfigParser
Requires-Dist: boto3
Requires-Dist: requests
